avi/__init__.py
avi/a1.py
avi/a2.py
avitutorial/__init__.py
avitutorial/a1.py
avitutorial/a2.py
avitutorial-0.0.1.dist-info/LICENSE
avitutorial-0.0.1.dist-info/METADATA
avitutorial-0.0.1.dist-info/WHEEL
avitutorial-0.0.1.dist-info/top_level.txt
avitutorial-0.0.1.dist-info/RECORD
