Metadata-Version: 2.1
Name: avitutorial
Version: 0.0.1
Summary: avitutorial
Home-page: UNKNOWN
Author: Pranay
Author-email: pranaysatija7@gmail.com
License: UNKNOWN
Keywords: arithmetic,math,mathematics,python tutorial,pranay satija
Platform: UNKNOWN
Classifier: Development Status :: 1 - Planning
Classifier: Intended Audience :: Developers
Classifier: Programming Language :: Python :: 3
Classifier: Operating System :: Unix
Classifier: Operating System :: MacOS :: MacOS X
Classifier: Operating System :: Microsoft :: Windows
License-File: LICENSE
